dagmc_bounding_box/__init__.py
dagmc_bounding_box/_version.py
dagmc_bounding_box/core.py
dagmc_bounding_box-0.2.1.dist-info/LICENSE.txt
dagmc_bounding_box-0.2.1.dist-info/METADATA
dagmc_bounding_box-0.2.1.dist-info/WHEEL
dagmc_bounding_box-0.2.1.dist-info/top_level.txt
dagmc_bounding_box-0.2.1.dist-info/RECORD
