Metadata-Version: 2.1
Name: dagmc-bounding-box
Version: 0.2.1
Summary: Find the bounding box and other related properties of a DAGMC h5m file
Home-page: https://github.com/fusion-energy/dagmc_bounding_box
Author: The dagmc_bounding_box Development Team
Author-email: mail@jshimwell.com
License: MIT
Project-URL: Source, https://github.com/fusion-energy/dagmc_bounding_box
Project-URL: Tracker, https://github.com/fusion-energy/dagmc_bounding_box/issues
Classifier: Natural Language :: English
Classifier: Topic :: Scientific/Engineering
Classifier: Programming Language :: Python :: 3
Classifier: Programming Language :: Python :: 3.6
Classifier: Programming Language :: Python :: 3.7
Classifier: Programming Language :: Python :: 3.8
Classifier: Programming Language :: Python :: 3.9
Classifier: License :: OSI Approved :: MIT License
Classifier: Operating System :: OS Independent
Requires-Python: >=3.6
License-File: LICENSE.txt
Requires-Dist: h5py
Requires-Dist: meshio
Requires-Dist: trimesh
Provides-Extra: tests
Requires-Dist: pytest (>=5.4.3) ; extra == 'tests'
Requires-Dist: pytest-cov ; extra == 'tests'
